{"errors":[],"warnings":[],"namedChunkGroups":{"app":{"chunks":[5,0,2],"assets":["webpack-runtime-809f470e1e42f6b6b655.js","webpack-runtime-809f470e1e42f6b6b655.js.map","commons-51a7ce5a413ec4625070.js","commons-51a7ce5a413ec4625070.js.map","app-4511177a55cc6ea93875.js","app-4511177a55cc6ea93875.js.map"],"children":{},"childAssets":{}},"component---src-pages-404-js":{"chunks":[1,0,3],"assets":["styles.7287d78bc1cec856532e.css","styles-afa82b7f2503727c8c2c.js","styles-afa82b7f2503727c8c2c.js.map","commons-51a7ce5a413ec4625070.js","commons-51a7ce5a413ec4625070.js.map","component---src-pages-404-js-214a06fe1c8c2ace6b33.js","component---src-pages-404-js-214a06fe1c8c2ace6b33.js.map"],"children":{},"childAssets":{}},"component---src-pages-index-js":{"chunks":[1,0,4],"assets":["styles.7287d78bc1cec856532e.css","styles-afa82b7f2503727c8c2c.js","styles-afa82b7f2503727c8c2c.js.map","commons-51a7ce5a413ec4625070.js","commons-51a7ce5a413ec4625070.js.map","component---src-pages-index-js-04c30727b0dca5759394.js","component---src-pages-index-js-04c30727b0dca5759394.js.map"],"children":{},"childAssets":{}}},"assetsByChunkName":{"app":["webpack-runtime-809f470e1e42f6b6b655.js","commons-51a7ce5a413ec4625070.js","app-4511177a55cc6ea93875.js"],"component---src-pages-404-js":["styles.7287d78bc1cec856532e.css","styles-afa82b7f2503727c8c2c.js","commons-51a7ce5a413ec4625070.js","component---src-pages-404-js-214a06fe1c8c2ace6b33.js"],"component---src-pages-index-js":["styles.7287d78bc1cec856532e.css","styles-afa82b7f2503727c8c2c.js","commons-51a7ce5a413ec4625070.js","component---src-pages-index-js-04c30727b0dca5759394.js"]}}